{
 "startsAt": 0,
 "problem": {
  "field": {
   "size": 24,
   "entities": [
    149,
    63,
    174,
    246,
    9,
    126,
    235,
    203,
    110,
    152,
    48,
    244,
    152,
    20,
    77,
    284,
    134,
    124,
    21,
    122,
    98,
    276,
    229,
    19,
    281,
    252,
    155,
    28,
    28,
    162,
    189,
    200,
    212,
    269,
    178,
    132,
    215,
    98,
    186,
    215,
    72,
    260,
    65,
    174,
    131,
    147,
    116,
    117,
    247,
    137,
    39,
    7,
    173,
    137,
    192,
    262,
    5,
    69,
    136,
    234,
    2,
    6,
    12,
    52,
    212,
    228,
    109,
    129,
    280,
    105,
    232,
    273,
    103,
    202,
    151,
    282,
    233,
    163,
    112,
    49,
    140,
    46,
    83,
    109,
    199,
    33,
    74,
    7,
    241,
    255,
    78,
    218,
    211,
    38,
    208,
    164,
    70,
    273,
    170,
    252,
    136,
    279,
    222,
    61,
    229,
    283,
    100,
    144,
    153,
    261,
    85,
    15,
    167,
    144,
    37,
    260,
    118,
    199,
    82,
    13,
    77,
    4,
    195,
    148,
    195,
    159,
    265,
    185,
    225,
    58,
    207,
    256,
    124,
    75,
    233,
    120,
    23,
    143,
    81,
    216,
    244,
    75,
    236,
    239,
    89,
    254,
    13,
    248,
    271,
    79,
    36,
    64,
    90,
    198,
    129,
    160,
    226,
    157,
    196,
    22,
    161,
    60,
    183,
    287,
    18,
    175,
    283,
    175,
    32,
    39,
    54,
    139,
    267,
    57,
    145,
    79,
    204,
    236,
    214,
    191,
    209,
    187,
    130,
    140,
    262,
    213,
    206,
    138,
    187,
    46,
    179,
    84,
    114,
    227,
    205,
    133,
    180,
    10,
    246,
    171,
    104,
    135,
    258,
    221,
    11,
    29,
    44,
    282,
    259,
    72,
    161,
    82,
    130,
    80,
    183,
    226,
    122,
    15,
    127,
    171,
    164,
    105,
    209,
    275,
    211,
    225,
    132,
    165,
    60,
    198,
    25,
    49,
    65,
    168,
    287,
    191,
    123,
    205,
    238,
    128,
    249,
    53,
    54,
    271,
    108,
    169,
    2,
    3,
    219,
    53,
    59,
    265,
    284,
    163,
    17,
    169,
    165,
    232,
    47,
    83,
    51,
    210,
    104,
    192,
    206,
    237,
    253,
    213,
    196,
    143,
    278,
    240,
    207,
    99,
    222,
    88,
    31,
    112,
    235,
    1,
    78,
    118,
    286,
    71,
    9,
    0,
    158,
    177,
    153,
    239,
    138,
    80,
    85,
    250,
    279,
    268,
    30,
    270,
    272,
    251,
    178,
    277,
    91,
    274,
    230,
    56,
    110,
    35,
    179,
    285,
    87,
    166,
    202,
    256,
    14,
    26,
    149,
    125,
    285,
    188,
    67,
    154,
    134,
    70,
    278,
    257,
    91,
    255,
    120,
    217,
    266,
    19,
    170,
    93,
    263,
    33,
    181,
    203,
    218,
    264,
    231,
    259,
    223,
    27,
    148,
    217,
    194,
    51,
    121,
    115,
    180,
    254,
    243,
    55,
    17,
    200,
    58,
    230,
    52,
    182,
    150,
    237,
    42,
    5,
    37,
    272,
    197,
    34,
    154,
    126,
    241,
    8,
    10,
    59,
    119,
    14,
    68,
    3,
    76,
    274,
    30,
    281,
    190,
    25,
    50,
    201,
    251,
    111,
    36,
    92,
    123,
    114,
    21,
    41,
    43,
    157,
    214,
    107,
    145,
    193,
    172,
    24,
    116,
    27,
    182,
    184,
    267,
    201,
    275,
    280,
    276,
    131,
    18,
    234,
    264,
    31,
    263,
    181,
    103,
    64,
    62,
    55,
    228,
    16,
    8,
    227,
    102,
    242,
    107,
    32,
    101,
    38,
    20,
    142,
    133,
    159,
    249,
    127,
    50,
    247,
    184,
    277,
    204,
    224,
    34,
    160,
    231,
    111,
    47,
    189,
    48,
    250,
    240,
    41,
    176,
    29,
    63,
    156,
    155,
    57,
    95,
    243,
    208,
    97,
    24,
    95,
    119,
    62,
    146,
    84,
    16,
    92,
    68,
    35,
    176,
    158,
    162,
    172,
    66,
    40,
    286,
    101,
    177,
    73,
    258,
    76,
    186,
    146,
    142,
    245,
    173,
    26,
    185,
    166,
    6,
    245,
    210,
    96,
    86,
    167,
    88,
    266,
    44,
    242,
    22,
    0,
    89,
    12,
    108,
    219,
    74,
    87,
    23,
    268,
    216,
    248,
    73,
    61,
    168,
    115,
    96,
    150,
    139,
    141,
    86,
    194,
    190,
    156,
    125,
    93,
    224,
    128,
    67,
    1,
    94,
    147,
    90,
    81,
    11,
    66,
    238,
    223,
    42,
    261,
    220,
    56,
    113,
    94,
    188,
    121,
    99,
    106,
    100,
    4,
    45,
    117,
    253,
    193,
    141,
    102,
    71,
    135,
    40,
    197,
    269,
    97,
    45,
    43,
    257,
    106,
    220,
    113,
    221,
    151,
    270,
    69
   ]
  }
 }
}